rhizonet/__init__.py
rhizonet/common.py
rhizonet/postprocessing.py
rhizonet/predict2d.py
rhizonet/prepare_patches.py
rhizonet/rhizonet.py
rhizonet/simpleLogger.py
rhizonet/train.py
rhizonet/unet2D.py
rhizonet/utils.py
rhizonet_package-0.0.2.dist-info/LICENSE
rhizonet_package-0.0.2.dist-info/METADATA
rhizonet_package-0.0.2.dist-info/WHEEL
rhizonet_package-0.0.2.dist-info/entry_points.txt
rhizonet_package-0.0.2.dist-info/top_level.txt
rhizonet_package-0.0.2.dist-info/RECORD
