Metadata-Version: 2.1
Name: rhizonet-package
Version: 0.0.2
Summary: Python package for RhizoNet-package
Author-email: Zineb Sordo <zsordo@lbl.gov>
License: MIT License
Project-URL: Homepage, https://github.com/zineb-sordo/rhizonet-package
Keywords: rhizonet-package
Classifier: Intended Audience :: Developers
Classifier: License :: OSI Approved :: MIT License
Classifier: Natural Language :: English
Classifier: Programming Language :: Python :: 3.8
Classifier: Programming Language :: Python :: 3.9
Classifier: Programming Language :: Python :: 3.10
Classifier: Programming Language :: Python :: 3.11
Classifier: Programming Language :: Python :: 3.12
Requires-Python: >=3.8
License-File: LICENSE
Requires-Dist: cachetools ==5.3.1
Requires-Dist: constants ==0.6.0
Requires-Dist: contourpy ==1.1.1
Requires-Dist: einops ==0.8.0
Requires-Dist: gitdb ==4.0.10
Requires-Dist: GitPython ==3.1.37
Requires-Dist: graphviz ==0.20.1
Requires-Dist: imageio ==2.31.5
Requires-Dist: joblib ==1.3.2
Requires-Dist: lightning ==2.0.9.post0
Requires-Dist: lightning-cloud ==0.5.39
Requires-Dist: lightning-utilities ==0.9.0
Requires-Dist: Markdown ==3.4.4
Requires-Dist: markdown-it-py ==3.0.0
Requires-Dist: matplotlib ==3.8.0
Requires-Dist: monai ==0.9.1
Requires-Dist: neptune ==1.8.1
Requires-Dist: networkx ==3.1
Requires-Dist: nibabel ==5.2.1
Requires-Dist: numpy ==1.26.4
Requires-Dist: oauthlib ==3.2.2
Requires-Dist: opencv-python ==4.8.1.78
Requires-Dist: pandas ==2.1.1
Requires-Dist: Pillow ==9.3.0
Requires-Dist: pytorch-lightning ==2.0.9.post0
Requires-Dist: requests ==2.31.0
Requires-Dist: scikit-image ==0.19.3
Requires-Dist: scikit-learn ==1.3.1
Requires-Dist: scipy ==1.10.0
Requires-Dist: tensorboard ==2.14.1
Requires-Dist: torch ==2.4.1
Requires-Dist: torchaudio ==2.4.1
Requires-Dist: torchdata ==0.8.0
Requires-Dist: torchmetrics ==1.2.0
Requires-Dist: torchtext ==0.18.0
Requires-Dist: torchvision ==0.19.1
Requires-Dist: torchviz ==0.0.2
Requires-Dist: tqdm ==4.66.1
Requires-Dist: uri-template ==1.3.0
Requires-Dist: urllib3 ==1.26.20
Requires-Dist: wandb ==0.18.3
Provides-Extra: all
Requires-Dist: rhizonet-package[extra] ; extra == 'all'
Provides-Extra: extra
Requires-Dist: pandas ; extra == 'extra'
